sigfox_api_client/__init__.py
sigfox_api_client/api_client.py
sigfox_api_client/configuration.py
sigfox_api_client/rest.py
sigfox_api_client/utils.py
sigfox_api_client/api/__init__.py
sigfox_api_client/api/api_users_api.py
sigfox_api_client/api/contract_infos_api.py
sigfox_api_client/api/coverages_api.py
sigfox_api_client/api/device_types_api.py
sigfox_api_client/api/devices_api.py
sigfox_api_client/api/groups_api.py
sigfox_api_client/api/profiles_api.py
sigfox_api_client/api/tiles_api.py
sigfox_api_client/api/users_api.py
sigfox_api_client/models/__init__.py
sigfox_api_client/models/action_job.py
sigfox_api_client/models/antenna.py
sigfox_api_client/models/api_user.py
sigfox_api_client/models/api_user_creation.py
sigfox_api_client/models/api_user_edition.py
sigfox_api_client/models/asynchronous_device_creation_job.py
sigfox_api_client/models/asynchronous_device_edition_job.py
sigfox_api_client/models/asynchronous_device_replacement_job.py
sigfox_api_client/models/asynchronous_device_transfer_job.py
sigfox_api_client/models/base_contact.py
sigfox_api_client/models/base_convention.py
sigfox_api_client/models/base_device_type.py
sigfox_api_client/models/base_geolocation.py
sigfox_api_client/models/base_host.py
sigfox_api_client/models/base_intervention.py
sigfox_api_client/models/base_maintenance.py
sigfox_api_client/models/base_provider.py
sigfox_api_client/models/base_response.py
sigfox_api_client/models/base_site.py
sigfox_api_client/models/base_station.py
sigfox_api_client/models/basic.py
sigfox_api_client/models/basic_create.py
sigfox_api_client/models/basic_update.py
sigfox_api_client/models/batch_url_callback.py
sigfox_api_client/models/billable_group.py
sigfox_api_client/models/bounds.py
sigfox_api_client/models/bulk_device_asynchronous_request.py
sigfox_api_client/models/bulk_unsubscribe.py
sigfox_api_client/models/callback.py
sigfox_api_client/models/callback_email.py
sigfox_api_client/models/callback_http.py
sigfox_api_client/models/callback_medium.py
sigfox_api_client-1.0.1.dist-info/METADATA
sigfox_api_client-1.0.1.dist-info/WHEEL
sigfox_api_client-1.0.1.dist-info/top_level.txt
sigfox_api_client-1.0.1.dist-info/RECORD
