Metadata-Version: 2.1
Name: sigfox-api-client
Version: 1.0.1
Summary: Sigfox API
Home-page: 
Author-email: 
Keywords: Swagger,Sigfox API
Requires-Dist: urllib3 >=1.15
Requires-Dist: six >=1.10
Requires-Dist: certifi
Requires-Dist: python-dateutil
